tlp_client/__init__.py
tlp_client-3.22.2.data/scripts/tlp-api-cli
tlp_client-3.22.2.data/scripts/tlp-player-urlgen
tlp_client-3.22.2.data/scripts/tlp-transedit-urlgen
tlp_client-3.22.2.dist-info/LICENSE
tlp_client-3.22.2.dist-info/METADATA
tlp_client-3.22.2.dist-info/WHEEL
tlp_client-3.22.2.dist-info/top_level.txt
tlp_client-3.22.2.dist-info/RECORD
