Metadata-Version: 2.1
Name: tlp-client
Version: 3.22.2
Summary: The MLLP-VRAIN's transLectures Platform (TLP) Python3 API client library and tools
Home-page: https://www.mllp.upv.es
Author: MLLP-VRAIN
Author-email: mllp-support@upv.es
License: UNKNOWN
Project-URL: Documentation (TLP Platform), https://ttp.mllp.upv.es/doc
Project-URL: Documentation (library), https://ttp.mllp.upv.es/doc/clients/python3
Platform: UNKNOWN
Classifier: Development Status :: 5 - Production/Stable
Classifier: Programming Language :: Python :: 3
Classifier: License :: OSI Approved :: Apache Software License
Classifier: Operating System :: OS Independent
Requires-Python: >=3.5
Requires-Dist: requests
Requires-Dist: requests-toolbelt (==0.10.1)
Requires-Dist: urllib3 (<2.0)
